[{"senderKeyId":737202140,"senderChainKey":{"iteration":26,"seed":"SAxGBHK5xdUVAH2DH2BBFSAGLrXgSCgDkRVXmD08v3o="},"senderSigningKey":{"public":"BcogZVDgp4LHWo1Ru5jdWRnakZvAYTWwuTywAThG3TB6"},"senderMessageKeys":[{},{},{},{},{},{},{},{},{},{},{},{},{},{},{},{},{},{},{},{},{},{},{},{}]},{"senderKeyId":91534832,"senderChainKey":{"iteration":46,"seed":"qUZhtF3YNDpF+bYWh0+Ez0fPQm8cuM/vIKHz1W/6zmU="},"senderSigningKey":{"public":"BeYyPOkNsShAwV7cMi3riMyu9N5iYQ1pJwaKLdZvavwM"},"senderMessageKeys":[{},{},{},{},{},{},{},{},{},{},{},{},{},{},{},{},{},{},{},{},{},{},{},{},{},{},{},{},{},{},{},{},{},{},{},{},{}]}]